{
  "id": "act-zm-2013-002-the-national-health-research",
  "type": "act",
  "jurisdiction": "ZM",
  "title": "The National Health Research",
  "citation": "Act No. 2 of 2013",
  "enacted_date": "2013-01-01",
  "commencement_date": null,
  "in_force": true,
  "amended_by": [],
  "repealed_by": null,
  "sections": [
    {
      "number": "1",
      "heading": "Short title",
      "text": "Short title"
    },
    {
      "number": "2",
      "heading": "Interpretation",
      "text": "Interpretation"
    },
    {
      "number": "3",
      "heading": "Application and scope",
      "text": "PART II\nTHE NATIONAL HEALTH RESEARCH AUTHORITY"
    },
    {
      "number": "4",
      "heading": "Establishment of National Health Research Authority",
      "text": "Establishment of National Health Research Authority"
    },
    {
      "number": "5",
      "heading": "Functions of Authority",
      "text": "Functions of Authority"
    },
    {
      "number": "6",
      "heading": "Powers of Authority",
      "text": "Powers of Authority"
    },
    {
      "number": "7",
      "heading": "Council of Authority",
      "text": "Council of Authority"
    },
    {
      "number": "8",
      "heading": "Exercise of functions and powers of Authority",
      "text": "Exercise of functions and powers of Authority"
    },
    {
      "number": "9",
      "heading": "Committees of Council",
      "text": "Committees of Council"
    },
    {
      "number": "10",
      "heading": "Delegation of functions",
      "text": "Delegation of functions"
    },
    {
      "number": "11",
      "heading": "Director",
      "text": "Director"
    },
    {
      "number": "12",
      "heading": "Secretary, inspectors and other staff of Authority",
      "text": "PART III\nTHE NATIONAL HEALTH RESEARCH ETHICS SYSTEM"
    },
    {
      "number": "13",
      "heading": "National Health Research Ethics Board",
      "text": "National Health Research Ethics Board"
    },
    {
      "number": "14",
      "heading": "Functions of Board",
      "text": "Functions of Board"
    },
    {
      "number": "15",
      "heading": "Tenure of office and vacancy of Board",
      "text": "Tenure of office and vacancy of Board"
    },
    {
      "number": "16",
      "heading": "Proceedings of Board",
      "text": "Proceedings of Board"
    },
    {
      "number": "17",
      "heading": "Research protocol",
      "text": "Research protocol"
    },
    {
      "number": "18",
      "heading": "Health research ethics committees",
      "text": "Health research ethics committees"
    },
    {
      "number": "19",
      "heading": "Functions and procedures of health research ethics",
      "text": "committee\nSingle copies of this Act may be obtained from the Government Printer,\nP.O. Box 30136, 10101 Lusaka. Price K23.00\n4 No. 2 of 2013] National Health Research"
    },
    {
      "number": "20",
      "heading": "Misconduct by health researchers",
      "text": "Misconduct by health researchers"
    },
    {
      "number": "21",
      "heading": "Complaints",
      "text": "Complaints"
    },
    {
      "number": "22",
      "heading": "Immunity from liability or penalty",
      "text": "Immunity from liability or penalty"
    },
    {
      "number": "23",
      "heading": "Reports by Board",
      "text": "Reports by Board"
    },
    {
      "number": "24",
      "heading": "Staff of Board",
      "text": "Staff of Board"
    },
    {
      "number": "25",
      "heading": "Disclosure of interest by members of Board",
      "text": "Disclosure of interest by members of Board"
    },
    {
      "number": "26",
      "heading": "Protection of personal information",
      "text": "Protection of personal information"
    },
    {
      "number": "27",
      "heading": "Immunity of member of Board or committee",
      "text": "Immunity of member of Board or committee"
    },
    {
      "number": "28",
      "heading": "Annual report of Board",
      "text": "Annual report of Board"
    },
    {
      "number": "29",
      "heading": "Appeals",
      "text": "Appeals"
    },
    {
      "number": "30",
      "heading": "Jurisdiction over offences committed outside Zambia",
      "text": "PART IV\nREGULATORY FRAMEWORK FOR HEALTH RESEARCH"
    },
    {
      "number": "31",
      "heading": "Priority areas for health research",
      "text": "Priority areas for health research"
    },
    {
      "number": "32",
      "heading": "Dissemination of health research information",
      "text": "Dissemination of health research information"
    },
    {
      "number": "33",
      "heading": "Access to, and deposition of, health research databases",
      "text": "Access to, and deposition of, health research databases"
    },
    {
      "number": "34",
      "heading": "Monitoring and evaluation",
      "text": "Monitoring and evaluation"
    },
    {
      "number": "35",
      "heading": "Partnerships in health research",
      "text": "Partnerships in health research"
    },
    {
      "number": "36",
      "heading": "Human research guidelines",
      "text": "Human research guidelines"
    },
    {
      "number": "37",
      "heading": "Consultation about regulatory framework",
      "text": "Consultation about regulatory framework"
    },
    {
      "number": "38",
      "heading": "Interim regulatory requirements",
      "text": "Interim regulatory requirements"
    },
    {
      "number": "39",
      "heading": "Revocation of regulatory frameworks",
      "text": "Revocation of regulatory frameworks"
    },
    {
      "number": "40",
      "heading": "Procedures for making submissions",
      "text": "Procedures for making submissions"
    },
    {
      "number": "41",
      "heading": "Health Research Trust Account",
      "text": "Health Research Trust Account"
    },
    {
      "number": "42",
      "heading": "Credit of amounts to Trust Account",
      "text": "Credit of amounts to Trust Account"
    },
    {
      "number": "43",
      "heading": "Purposes of Trust Account",
      "text": "Purposes of Trust Account"
    },
    {
      "number": "44",
      "heading": "Accounting for gifts and bequests",
      "text": "PART V\nHEALTH RESEARCH ON, OR EXPERIMENTATION WITH HUMAN\nPARTICIPANTS AND ANIMAL SUBJECTS"
    },
    {
      "number": "45",
      "heading": "Health research on, or experimentation with, human",
      "text": "participants or animal subjects"
    },
    {
      "number": "46",
      "heading": "Prohibition of reproductive cloning of human beings",
      "text": "Prohibition of reproductive cloning of human beings"
    },
    {
      "number": "47",
      "heading": "Prohibition of removal of tissue, organs, blood, blood",
      "text": "products or gametes from living persons for research\npurposes\nNational Health Research [ No. 2 of 2013 5\nPART VI\nBIOLOGICAL MATERIALS FOR HEALTH RESEARCH"
    },
    {
      "number": "48",
      "heading": "Purposes of collection of biological materials",
      "text": "Purposes of collection of biological materials"
    },
    {
      "number": "49",
      "heading": "Storage of biological materials",
      "text": "Storage of biological materials"
    },
    {
      "number": "50",
      "heading": "Exportation and importation of biological materials",
      "text": "Exportation and importation of biological materials"
    },
    {
      "number": "51",
      "heading": "Designation of institution as bio-bank",
      "text": "Designation of institution as bio-bank"
    },
    {
      "number": "52",
      "heading": "Searches at ports of entry, exit and sites",
      "text": "Searches at ports of entry, exit and sites"
    },
    {
      "number": "53",
      "heading": "Ownership of biological materials and material transfer",
      "text": "agreement\nPART VII\nCLINICAL TRIALS"
    },
    {
      "number": "54",
      "heading": "Clinical trials",
      "text": "PART VIII\nRSEARCH IN TRADITIONAL, COMPLEMENTARY AND ALTERNATIVE\nMEDICINE"
    },
    {
      "number": "55",
      "heading": "Research in traditional, complementary and alternative",
      "text": "medicine\nPART IX\nINTELLECTUAL PROPERTY RIGHTS"
    },
    {
      "number": "56",
      "heading": "Intellectual property rights",
      "text": "PART X\nGENERAL PROVISIONS"
    },
    {
      "number": "57",
      "heading": "Entry by inspectors or other authorised persons",
      "text": "Entry by inspectors or other authorised persons"
    },
    {
      "number": "58",
      "heading": "Duty to provide information to inspector",
      "text": "Duty to provide information to inspector"
    },
    {
      "number": "59",
      "heading": "Service of Notice",
      "text": "Service of Notice"
    },
    {
      "number": "60",
      "heading": "Authentication of documents",
      "text": "Authentication of documents"
    },
    {
      "number": "61",
      "heading": "General penalties for offences",
      "text": "General penalties for offences"
    },
    {
      "number": "62",
      "heading": "Offences by body corporation or an unincorporate body",
      "text": "Offences by body corporation or an unincorporate body"
    },
    {
      "number": "63",
      "heading": "Regulations",
      "text": "Regulations"
    },
    {
      "number": "64",
      "heading": "Transitional provisions",
      "text": "Schedule\nNational Health Research [ No. 2 of 2013 7\nGOVERNMENT OF ZAMBIA\nACT\nNo. 2 of 2013\nDate of Assent: 21/03/13\nAn Act to establish the National Health Research Authority\nand provide for its functions and powers; establish the\nNational Health Research Ethics Board and provide for its\nfunctions and powers; provide a regulatory framework for\nthe development, regulation, financing and coordination of\nhealth research and ensure the development of consistent\nhealth research standards and guidelines for ethically sound\nhealth research; provide for the establishment of health\nresearch ethics committees and the regulation and\nmanagement of research institutions, health researchers\nand health establishments involved in or undertaking\nresearch; provide for the regulation of biological material\nfor health research; provide for ethical approval for the\nconduct of clinical trials; provide for the use of traditional,\ncomplementary and alternative medicines in health\nresearch; provide for data management and intellectual\nproperty rights in health research; provide for the\ndesignation of bio banks; and provide for matters connected\nwith, or incidental to, the foregoing.\n[22nd March, 2013\nENACTED by the Parliament of Zambia.\nEnactment\nPART I\nPRELIMINARY"
    },
    {
      "number": "1",
      "heading": "This Act may be cited as the National Health Research Short title",
      "text": "Act, 2013."
    },
    {
      "number": "2",
      "heading": "In this Act, unless the context otherwise requires\u2014",
      "text": "Interpretation\n8 No. of 2013] National Health Research\n\u201c accreditation \u201d means a process of certification of\ncompetence in health research;\n\u201c animal subject \u201d means an animal which is used for health\nresearch or clinical trial;\n\u201c Authority \u201d means the National Health Research Authority\nestablished under section four;\n\u201c Board \u201d means the National Health Research Ethics Board\nconstituted under section thirteen;\n\u201c bio-bank \u201d means a collection of biological materials and\nthe associated data and information which is stored in an\norganised system;\nCap. 1\n\u201c biological materials \u201d means organs and parts of organs,\ncells and tissue, sub cellular structures and cell products,\nblood, saliva, sputum, gametes (sperm and ova), embryos\nand foetal tissue, waste, including urine, feaces, sweat,\nhair, epithelial scales, nail clippings, placenta and cell lines\nfrom human or animal tissue;\n\u201c blood product \u201d means any product derived or produced\nfrom blood, including circulating progenitor cells, bone\nmarrow progenitor cells and umbilical cord progenitor cells;\n\u201c Board Chairperson \u201d means the person appointed as\nChairperson of the Board in accordance with section\nthirteen;\n\u201c Cabinet \u201d has the meaning assigned to it in the Constitution;\n\u201c central health research repository \u201d means the central health\nresearch repository as prescribed by the Minister under\nsection thirty-three;\n\u201c Chairperson \u201d means the person appointed Chairperson of\nthe Council under section seven;\n\u201c clinical trial regulations \u201d means regulations made under\nsection fifty-four;\n\u201cclinical trial \u201d means a systematic study, involving human\nparticipants or animal subjects, that serves to answer\nspecific questions about the safety or efficacy of a medicine,\nvaccine or method of prevention or treatment;\n\u201c committee \u201d means a committee of the Council established\nunder section nine;\nNational Health Research [ No. 2 of 2013 9\n\u201c consent \u201d means a voluntary agreement to participate in\nhealth research by a person, who is not a minor, with full\nunderstanding of the potential risks and benefits of the\nhealth research;\n\u201c Council \u201d means the Council of the Authority constituted\nunder subsection seven;\n\u201c Director \u201d means the person appointed Director of the\nAuthority under section eleven;\n\u201c embryo \u201d means a human offspring in the first eight weeks\nfrom conception or animal offspring in the first trimester,\nthe gestation or incubation period for the relevant species\nas the case may be;\n\u201c ethical approval \u201d means approved by the Board for the\nconduct, in Zambia, of research on human participants or\nanimal subjects in accordance with sections fourteen and\nforty-five;\n\u201c genetic material \u201d means a part of a cell that carries\ninformation which can be inherited;\n\u201c health establishment \u201d means a public or private\nestablishment, including its facilities, buildings or other\nplaces, operated or designed to provide inpatient or\noutpatient treatment, diagnostic or therapeutic interventions,\nnursing, rehabilitative, palliative, convalescent, preventative\nor other health services;\n\u201c health research \u201d means an activity conducted which\u2014\n(a) contributes to knowledge of the biological, clinical,\npsychological or social processes in human beings\nor animals;\n(b) uses scientific methods to generate information to\ndeal with health and disease;\n(c) improves scientific methods for provision of health\nservices and human pathology;\n(d) investigates causes of disease and the effects of the\nenvironment on the human body; or\n(e) develops new applications of pharmaceuticals,\nmedicines and health technology;\n\u201c health research ethics committee \u201d means a committee registered\nand accredited by the Board under section eighteen;\n10 No. 2 of 2013] National Health Research\n\u201c health researcher \u201d means an individual who undertakes\nhealth research;\n\u201c human participant \u201d means any living person who consents\nto participate in a health research activity or a body of a\ndeceased person or part of a body of a deceased person\nCap. 306\nas provided in the Human Tissue Act;\n\u201c human research guidelines \u201d means guidelines for the\nconduct of health research involving human participants\nissued under section thirty-six;\n\u201c inspector \u201d means a person appointed by the Authority as\nan inspector for the purposes of this Act;\n\u201c national health research strategic plan \u201d means a national\nplan that prioritises health research as provided under\nsection thirty-one;\n\u201c intellectual property rights \u201d means an exclusive right granted\nto inventors and owners of works that are the result of\nhuman intellectual creativity;\n\u201c interim regulatory requirements \u201d means a regulatory\nframework issued under section thirty-eight;\n\u201c legal guardian \u201d means a person lawfully vested with the\npower, and charged with the obligation, of taking care of\nand managing the property and rights of a person who,\nbecause of age, understanding or self control, is incapable\nof administering that person\u2019s own affairs;\n\u201c material transfer agreement \u201d means a written contract\nbetwee"
    },
    {
      "number": "8",
      "heading": "Except as otherwise provided under this Act, the Council",
      "text": "Exercise of\nshall exercise the following functions and powers of the Authority: functions and\npowers of\n(a) set, review and enforce ethical standards and human and Authority\nanimal research ethical guidelines, including ethical\nstandards and guidelines for clinical trials;\n16 No. 2 of 2013] National Health Research\n(b) determine policy matters in health research;\n(c) review the policy and strategic plan of the Authority and\noversee the implementation and efficient operation of\nthe policy and functions of the Authority;\n(d) approve the annual budget and plans of the Authority;\n(e) monitor and evaluate the performance of the Authority\nagainst budgets and plans;\n(f) establish and approve conditions of service of the staff of\nthe Authority;\n(g) make recommendations to the Minister for amendments\nto this Act or issuance of regulations under this Act;\nand\n(h) perform any other function conferred or imposed on the\nCouncil by or under this Act.\n(2) The Minister may give to the Council general or specific\ndirections, consistent with this Act, relating to the discharge of the\nfunctions of the Authority and the Council shall give effect to those\ndirections.\nCommittees 9. (1) The Council may, for purposes of performing the\nof functions of the Authority, establish such committees as it considers\nCouncil\nnecessary for the effective exercise of the functions of the Authority.\n(2) The Council may appoint, as members of a committee, persons\nwho are or are not members of the Council, except that at least\none member of the Council shall be a member of a committee.\n(3) A person serving as a member of a committee shall hold\noffice for such period as the Council may determine.\n(4) Subject to any specific or general direction of the Council, a\ncommittee may regulate its own procedure.\nDelegation of 10. The Council may, by direction, in writing, and subject to\nfunctions such terms and conditions as it considers necessary, delegate to\nthe Director, any member or any committee any of the functions\nof the Authority.\nDirector 11. (1) The Council shall appoint, on such terms and conditions\nas it may determine, a Director who shall be the chief executive\nofficer of the Authority.\n(2) The Director shall be responsible, under the general direction\nof the Council, for\u2014\nNational Health Research [ No. 2 of 2013 17\n(a) the management and administration of the affairs of the\nAuthority;\n(b) the implementation of the decisions of the Council; and\n(c) any other function assigned or delegated to the Director\nby the Council or by or under this Act.\n(3) The Director shall attend meetings of the Council and may\naddress those meetings but shall not vote on any matter.\n(4) The person presiding at any meeting of the Council may\nrequest the Director to withdraw from the meeting."
    },
    {
      "number": "12",
      "heading": "The Council may appoint, on such terms and conditions Secretary,",
      "text": "inspectors\nas it may determine, the Secretary, inspectors and such other staff\nand other\nas may be necessary for the performance of the functions of the staff of\nAuthority. Authority\n(2) The Council shall provide an inspector with a certificate of\nappointment, in the prescribed form, which shall be prima facie\nevidence of the inspector\u2019s appointment.\nPART III\nTHE NATIONAL HEALTH RESEARCH ETHICS SYSTEM"
    },
    {
      "number": "13",
      "heading": "There is established the National Health Research National",
      "text": "Ethics Board which shall consist of one representative from each Health\nof the following disciplines and sectors: Research\nEthics\n(a) law;\nBoard\n(b) pharmacology;\n(c) pharmacy;\n(d) theology;\n(e) biostatistics;\n(f) epidemiology;\n(g) public health;\n(h) biomedical science;\n(i) veterinary medicine;\n(j) traditional medicine;\n(k) nursing;\n(l) social science; and\n(m) clinical medicine.\n(2) The members of the Board shall be appointed by the Council\nand shall serve on a part-time basis.\n(3) An organisation or association that represents members in\nthe disciplines or sectors stipulated in subsection (1) shall recommend\na representative for appointment as a member of the Board.\n18 No. 2 of 2013] National Health Research\n(4) The Chairperson of the Board shall be appointed by the\nCouncil from among the members of the Board.\n(5) The Vice-Chairperson of the Board shall be elected by the\nmembers from amongst themselves.\nFunctions of 14. (1) The Board shall regulate ethics on human and animal\nBoard research as provided by or under this Act, and oversee and ensure\nadherence to health research ethics as provided in the regulatory\nframework and ethics guidelines.\n(2) Notwithstanding the generality of subsection (1), the Board\nshall\u2014\n(a) regulate the conduct of research and monitor and evaluate\nall health research;\n(b) register and accredit health researchers and health\nresearch ethics committees;\n(c) regulate and monitor the conduct of health research and\nhealth research ethics committees;\n(d) institute such disciplinary action, as may be prescribed,\nagainst any health researcher or research institution\nfound to be in violation of any ethical standards or\nguidelines set for conducting of health research;\n(e) act as an appeals body from decisions of the health research\nethics committees;\n(f) adjudicate complaints about the functioning of health\nresearch ethics committees and hear any complaint\nby a health researcher regarding a health research ethics\ncommittee;\n(g) notify any violation of professional conduct to the\nappropriate professional association or statutory body;\n(h) create awareness among health research reviewers,\ndecision and policy makers and the community on the\nbasic principles of health research ethics;\n(i)promote training in health research ethics and support the\nformation of health research ethics committees;\n(j)audit health research ethics committees; and\n(k) review research proposals and research protocols in order\nto ensure that health research conducted by a research\ninstitution or health researcher promotes health,\ncontributes to the prevention of communicable or non-\nNational Health Research [ No. 2 of 2013 19\ncommunicable diseases or disability or results in cures\nfor communicable or non-communicable diseases and\nis in accordance with health research ethics.\n(3) The Board shall give ethical approval for\u2014\n(a) all clinical trials involving medicines, vaccines or other\nbiological products, new therapeutic regimes, as well as\ninvasive diagnostic procedures;\n(b) multi-center and multi-national collaborative health\nresearch;\n(c) health research which is fully or partially initiated, financed\nand wholly or partly carried out by external donors or\ninternational agencies;\n(d) health research which is carried out by an international\nagency or agencies with bilateral or multi-lateral\ncollaboration or agreements with the Government; and\n(e) health research proposals that meet the health research\nethics guidelines.\n(4) The Board may delegate any of its functions to an accredited\nhealth research ethics committee."
    },
    {
      "number": "15",
      "heading": "A member of the Board shall hold office for a period Tenure of",
      "text": "of three years from the date of appointment and is eligible for re- office and\nvacancy of\nappointment for one further term of three years. Board\n(2) A member may resign upon giving one month\u2019s notice, in\nwriting, to the Council.\n(3) The office of member becomes vacant \u2014\n(a) upon the member\u2019s death;\n(b) if the member is absent, without reasonable excuse, from\nthree consecutive meetings of the Board of which the\nmember had notice without the prior approval of the Board;\n(c) on ceasing to be a representative of the organisation or\nassociation which recommended the member;\n(d) if the member is found guilty of professional misconduct\nby the relevant professional association or statutory body;\n(e) if the member is convicted of an offence involving fraud\nor dishonesty;\n(f) if the member becomes mentally or physically incapable\nof performing the duties of a member; or\n(g) if the member is declared bankrupt.\n20 No. 2 of 2013] National Health Research\n(4) The Council may fill a vacancy on the Board by appointing\nanother person to replace the member who vacates office for the\nremainder of the term.\nProceedings 16. (1) The Board shall regulate its own procedures at meetings.\nof Board\n(2) The quorum at any meeting of the Board shall be eight\nmembers.\n(3) The disciplinary proceedings of the Board shall be as\nprescribed.\nResearch 17. All proposals for health research under this Act shall be\nprotocol reviewed by the Board or any other accredited health research\nethics committee, as may be prescribed, and shall be approved by\nthe Board."
    },
    {
      "number": "18",
      "heading": "A research institution and health establishment, at which",
      "text": "Health\nresearch health research is conducted, shall constitute health research ethics\nethics\ncommittees, which shall be registered with, and accredited by, the\ncommittees\nBoard or any other accredited health research ethics committee.\n(2) The members of a health research ethics committee shall be\nappointed by the respective research institution and the\nrepresentation shall be consistent in discipline as provided under\nsubsection (1) of section thirteen.\n(3) The Minister, in consultation with the Authority, shall, by\nstatutory instrument, make regulations for accrediting health\nresearchers and research institutions.\nFunctions and 19. (1) A health research ethics committee shall have such\nprocedures of functions and powers as may be prescribed.\nhealth research\nethics (2) A health research ethics committee shall comply with the\ncommittee\nprovisions of this Act.\n(3) A health research ethics committee shall regulate its own\nprocedure at meetings.\n(4) The disciplinary procedures for a health research ethics\ncommittee shall be as prescribed.\nMisconduct 20. (1) A health researcher commits misconduct if the health\nby researcher\u2014\nhealth\nresearchers (a) does not comply with a prescribed professional code of\nconduct;\n(b) conducts health research which involves human\nparticipants or potentially affects humans without first\nobtaining ethical approval under this Act or other\napprovals required under any other written law;\nNational Health Research [ No. 2 of 2013 21\n(c) collects samples or information from human participants\nwithout first obtaining consent from the participants in\naccordance with this Act;\n(d) shares samples collected from human participants with\nother health researchers or research institutions without\nfirst obtaining the relevant approvals under this Act;\n(e) shares samples collected from human participants without\nan approved material transfer agreement, as provided\nunder this Act;\n(f) shares samples collected prospectively from human\nparticipants with other health researchers or research\ninstitutions without the informed consent of the donors\nof the samples to do so;\n(g) fails to submit prescribed mandatory reports to a health\nresearch ethics committee and the Board;\n(h) fails to uphold privacy and confidentiality of participants\u2019\ninformation;\n(i) deviates from an approved research protocol;\n(j) fails to report deviations from an approved research\nprotocol to the relevant health research ethics committee\nor the Board;\n(k) fabricates, falsifies or knowingly plagiarises data; or\n(l) forges approvals or other relevant documents under this\nAct.\n(2) A health researcher who contravenes subsection (1) and\nwho is found guilty by a health research ethics committee or the\nBoard is liable to a fine not exceeding four hundred thousand penalty\nunits or shall be banned from conducting health research for a\nminimum of five years.\n(3) Notwithstanding subsection (2), a health researcher who\ncommits a criminal offence is liable to prosecution.\n(4) The Minister shall, in consultation with the Authority, by\nstatutory instrument, issue regulations for dealing with misconduct\nby health researchers and procedures for their discipline."
    },
    {
      "number": "21",
      "heading": "A health researcher or research institution whose Complaints",
      "text": "interests are affected by an action or decision of a health research\n22 No. 2 of 2013] National Health Research\nethics committee may lodge a complaint with the Board and request\nan investigation concerning the action or decision of the health\nresearch ethics committee, on one or more of the grounds set out\nin subsection (2).\n(2) A health researcher or research institution, referred to in\nsubsection (1), may lodge a complaint on any of the following\ngrounds:\n(a) that the action or decision breached the rules of natural\njustice;\n(b) that the action or decision was induced or affected by\nfraud;\n(c) that there was no evidence or other material to justify the\naction or decision;\n(d) that an irrelevant consideration was taken into account in\nrelation to the action;\n(e) that a relevant consideration was not taken into account\nin relation to the action or decision;\n(f) that in the course of the decision making process, a\ndiscretionary power was exercised for a purpose other\nthan the purpose for which the power was conferred;\n(g) that the action or decision involved the exercise of a\ndiscretionary power in bad faith;\n(h) that, in the course of the decision making process, a\npersonal discretionary power was exercised at the\ndirection of another person;\n(i) that the decision involved the exercise of a discretionary\npower in accordance with a rule or policy without regard\nto the merits of the particular case; or\n(j) that the exercise of the power was done in a way that\nconstituted an abuse of the power.\n(3) A complaint shall\u2014\n(a) be in writing;\n(b) be signed by the complainant;\n(c) describe the action complained about;\n(d) specify the nature of, and grounds for, the complaint; and\n(e) be lodged with the Board.\nNational Health Research [ No. 2 of 2013 23\n(4) The Board shall investigate a complaint concerning an action\nor decision of a health research ethics committee if a complaint is\nlodged with it or on its own initiative.\n(5) The Board may decide not to investigate a complaint lodged\nunder this section or decide to discontinue an investigation if it\u2014\n(a) is satisfied that the complainant became aware of the\nmatter constituting a ground for the complaint more than\ntwelve months before making the complaint to the Board;\nor\n(b) has reasonable grounds for believing that \u2014\n(i) the complaint is frivolous or vexatious or is not\nmade in good faith; or\n(ii) the investigation or any further investigation of\nthe action is not justified in all the circumstances.\n(6) The Board shall, if it decides not to investigate a complaint or\nto discontinue an investigation, give the complainant written notice\nof the decision, which shall include the reasons for the decision.\n(7) The Minister shall prescribe the manner, form and process\nfor investigating, hearing and deciding on complaints by the Board."
    },
    {
      "number": "22",
      "heading": "A person who is requested by the Board or a health Immunity",
      "text": "research ethics committee to\u2014 from\nliability or\n(a) provide information, documents or other records; or penalty\n(b) answer a question;\nto assist the Board or a health research ethics committee in its\ninvestigation on a matter shall not be subject to any liability or\npenalty under this Act or any other written law."
    },
    {
      "number": "23",
      "heading": "The Board shall make a report to the Council where, Reports by",
      "text": "upon investigating a complaint concerning an action or decision of Board\na health research ethics committee, it determines that the action\nwas based on one of the grounds set out in section twenty.\n(2) A copy of the report of the Board shall be submitted to the\nMinister and the person responsible for, or board of, the relevant\nresearch institution, health researcher or health establishment and\nto the complainant.\n(3) The Council shall ensure, having regard to the\nrecommendations made in the report of the Board, that the relevant\nresearch institution, health researcher or health establishment\u2014\n24 No. 2 of 2013] National Health Research\n(a) takes whatever action that the Board considers\nappropriate; and\n(b) informs the complainant of the action that the research\ninstitution, health researcher or health establishment has\ntaken and of its reasons for taking the action.\nStaff of 24. The Authority shall\u2014\nBoard\n(a) second staff to service the Board; and\n(b) provide to the Board facilities necessary for it to perform\nits functions and exercise its powers under this Act.\nDisclosure of 25. (1) Where the Board is investigating, or is to investigate, a\ninterest by complaint concerning an action or decision of a health research\nmembers of\nethics committee and a member of the Board has, or acquires, an\nBoard\ninterest that could conflict with the proper performance of the\nmember\u2019s functions in relation to the investigation, the member\nshall disclose the interest to the Board and the member shall only\ntake part in the investigation if the complainant and the Board agree\nthat the member may so take part.\n(2) If, in relation to an investigation of a complaint by the Board\u2014\n(a) a member discloses an interest under subsection (1); and\n(b) the complainant and the Board do not agree to the member\ntaking part in the investigation;\nthe member shall not take part in the investigation of the complaint.\nProtection of 26. (1) The Board shall not, except in the performance or\npersonal exercise of its functions or powers under this Act, make a record\ninformation\nof or disclose to any person any information about another person\nthat the Board has access to in the performance or exercise of its\nfunctions or powers under this Act.\n(2) Except for the purposes of this Act, if the Board has possession\nof a document or other record or notice of a matter or thing as a\nresult of its functions or powers under this Act, a court shall not\nrequire the Board to\u2014\n(a) produce the document or other record in its possession;\nor\n(b) disclose the matter or thing of which it had notice.\nImmunity of 27. An action or other proceeding shall not lie or be instituted\nmember of against a member of the Board or a committee, or in respect of,\nBoard or\ncommittee any act or thing done or omitted to be done in good faith in the\nNational Health Research [ No. 2 of 2013 25\nexercise of or performance, or purported exercise or performance\nof any of the powers, functions or duties conferred under this Act."
    },
    {
      "number": "28",
      "heading": "The Board shall, as soon as practicable after the end of Annual",
      "text": "report of\neach financial year, give the Authority a written report of the Board\u2019s\nBoard\nactivities during that year."
    },
    {
      "number": "29",
      "heading": "A person who is aggrieved with the decision of the Appeals",
      "text": "Board may, within fourteen days of service of the decision, appeal\nto the Council and thereafter may appeal to a court of competent\njurisdiction.\n(2) A decision of the Board made under this section shall not\ntake effect until the expiration of the time for lodging an appeal, the\nappeal is withdrawn or disposed of."
    },
    {
      "number": "30",
      "heading": "Where a health researcher has committed an offence for",
      "text": "Jurisdiction\nwhich the health researcher has been punished in another country over offences\ncommitted\nand what the health researcher did constitutes a misconduct under outside\nthis Act, that health researcher shall be banned, by the Council on Zambia\nthe recommendation of the Board, from conducting health research\nin Zambia.\nPART IV\nREGULATORY FRAMEWORK FOR HEALTH RESEARCH"
    },
    {
      "number": "31",
      "heading": "The Authority shall identify and prioritise areas for Priority area",
      "text": "health research and advise the Minister, who shall recommend the for health\nresearch\npriority areas to Cabinet for approval as national health research\npriority areas which shall be incorporated in a national health\nresearch strategic plan.\n(2) The Authority shall, in identifying priorities for health research,\ntake into consideration\u2014\n(a) the burden of disease in the country;\n(b) the cost effectiveness of interventions aimed at reducing\nthe burden of disease;\n(c) the availability of resources for the implementation of an\nintervention at the level closest to the affected\ncommunities;\n(d) the health needs of special groups;\n(e) the health needs of communities; and\n(f) emerging public health problems.\n26 No. 2 of 2013] National Health Research\n(3) A health researcher and research institution shall align health research\nactivities to the subsisting national health research strategic plan.\n(4) The Authority may allow research outside a national research\nstrategic plan if it is in the public interest or public policy so requires.\nDissemination 32. (1) The Minister, in consultation with the Authority, shall\nof health prescribe mechanisms for dissemination of health research\nresearch\ninformation as follows:\ninformation\n(a) any health research conducted in Zambia shall first be\ndisseminated locally before being disseminated outside\nZambia; and\n(b) any person intending to publish health research information\nfor health research undertaken in Zambia shall first notify\nthe Authority, in writing, citing the research title and the\nethical approval obtained from the Board.\n(2) The Authority may, for the purposes of disseminating health\nresearch information, facilitate fora or media through which health\nresearch information may be disseminated, timely, to a broad\naudience in Zambia.\n(3) A person shall not disseminate information that is identifiable\nwithout\u2014\n(a) the written consent of the source of the information; and\n(b) approval from the responsible authority.\n(4) The Authority may, under such circumstances as it considers\nnecessary, make exemptions in relation to the dissemination of\ninformation as provided under this section."
    },
    {
      "number": "33",
      "heading": "The Authority has the right to access all health research",
      "text": "Access to, and\ndeposition of, databases in Zambia.\nhealth research\ndatabases (2) The Minister, in consultation with the Authority, shall put in\nplace a national system for \u2014\n(a) creating and securing health research databases;\n(b) storing and retrieving health research data; and\n(c) disseminating health research data from the national\nsystem.\n(3) The Minister may, in consultation with the Authority, by\nstatutory instrument, make regulations for ensuring that databases\nfor internally and externally funded health research are kept in a\ncentral health research repository as prescribed by the Minister.\nNational Health Research [ No. 2 of 2013 27\n(4) The Authority has the right to access databases, bio banks\nor any information collected by health researchers and research\ninstitutions."
    },
    {
      "number": "34",
      "heading": "The Authority shall \u2014",
      "text": "Monitoring\nand\n(a) develop monitoring and evaluation mechanisms for all evaluation\nhealth research programmes and activities;\n(b) promote training of health workers in health research\nmethodologies and ethics, documentation, monitoring\nand evaluation; and\n(c) monitor and evaluate ongoing health research programmes\nand activities being undertaken in Zambia."
    },
    {
      "number": "35",
      "heading": "The Minister may, in consultation with the Authority \u2014 Partnerships",
      "text": "in health\n(a) establish mechanisms for involving communities in health research\nresearch;\n(b) facilitate the establishment of a consultative forum for\nwide dissemination of national health research priority\nareas and outputs; and\n(c) make regulations for the protection of interests of\nstakeholders and the sharing of risks, benefits and\noutputs in health research programmes and activities."
    },
    {
      "number": "36",
      "heading": "Without limiting any of the matters on which the Council Human",
      "text": "may issue guidelines under this Act, the Council shall issue guidelines research\nguidelines\non the conduct of human research.\n(2) The Council shall issue guidelines on the conduct of human\nresearch in collaboration with the Board."
    },
    {
      "number": "37",
      "heading": "The Minister, in consultation with the Authority, shall, Consultation",
      "text": "before issuing any proposed regulatory framework, consult with about\nregulatory\nrelevant stakeholders in accordance with this section, except that framework\nthis section shall not apply\u2014\n(a) to a statutory instrument; or\n(b) if the proposed regulatory framework is urgent or is of\nminor significance, as the Minister may determine.\n(2) If the Minister, in consultation with the Authority, intends to\nissue any regulatory framework, the Minister shall publish a notice,\nin the Gazette or in a daily newspaper of general circulation in\nZambia\u2014\n28 No. 2 of 2013] National Health Research\n(a) stating the intention to issue the regulatory framework;\nand\n(b) inviting persons or bodies to make submissions relating to\nthe proposed regulatory framework in accordance with\nthe procedures, and within the period, specified in the\nnotice.\n(3) As soon as practicable after the end of the period specified\nunder paragraph (b) of subsection (2), the Minister, in consultation\nwith the Authority, shall, having regard to any submissions received\npursuant to the invitation referred to in that paragraph\u2014\n(a) prepare a draft of the regulatory framework and publish\na notice, in the Gazette and in a daily newspaper of\ngeneral circulation in Zambia\u2014\n(i)containing a summary of the provisions of the draft\nregulatory framework;\n(ii) stating where copies of the draft regulatory\nframework may be obtained; and\n(iii) inviting persons or bodies to make submissions\nrelating to the draft regulatory framework in\naccordance with the procedures, and within the\nperiod, specified in the notice; or\n(b) publish a notice, in the Gazette and in a daily\nnewspaper of general circulation in Zambia, stating\nthat it no longer proposes to issue the regulatory\nframework.\n(4) The Minister, in consultation with the Authority, shall take\ninto account any submissions received pursuant to the invitation\nreferred to in subparagraph (iii) of paragraph (a) of subsection (3)\nbefore issuing the proposed regulatory framework.\nInterim 38. (1) The Minister, in consultation with the Authority, may\nregulatory make interim regulatory requirements and issue the requirements\nrequirements\nwithout following the procedure provided in section thirty-seven\nif a matter \u2014\n(a) would ordinarily be the subject of a regulatory framework;\n(b) needs, for any reason or circumstance, to be dealt with\nurgently; and\nNational Health Research [ No. 2 of 2013 29\n(c) raises issues that are of minor significance;\nand shall publish a notice, in the Gazette or a daily newspaper\nof general circulation in Zambia, stating the reasons for not following\nthe procedures provided under section thirty-seven.\n(2) Notwithstanding subsection (1), the Minister, in consultation\nwith the Authority, shall, within thirty days of the issue of an interim\nregulatory requirement, publish a notice in the manner and form\nprescribed\u2014\n(a) setting out the reasons for issuing the interim regulatory\nrequirement and a summary of the interim\nregulatory requirement; and\n(b) inviting persons or bodies to make submissions to the\nMinister on the interim regulatory requirement, within\nthe period specified in the notice.\n(3) If the Minister fails, within forty-five days after the end of\nthe period specified in subsection (2), to comply with the\nprocedures provided for in subsection (2), any interim regulatory\nrequirement shall be revoked on the forty-fifth day."
    },
    {
      "number": "39",
      "heading": "The Minister, in consultation with the Authority, may,",
      "text": "Revocation of\nwithout undertaking consultation, revoke any regulatory framework regulatory\nframeworks\nor interim regulatory requirements."
    },
    {
      "number": "40",
      "heading": "The Authority shall develop and publish procedures to Procedures",
      "text": "for making\nassist persons or bodies to make submissions under this Part.\nsubmissions"
    },
    {
      "number": "41",
      "heading": "There shall be established a Health Research Trust Health",
      "text": "Account. Research\nTrust\nAccount\n(2) The Trust Account shall be opened as a special account, in a\ncommercial bank, for the purposes of the Public Finance Act, 2004. Act No. 15\nof 2004\n(3) If interest is received by the Authority from the investment\nof an amount standing to the credit of the Trust Account, an amount\nequal to the interest shall be credited to the Trust Account."
    },
    {
      "number": "42",
      "heading": "There shall be credited to the Trust Account amounts Credit of",
      "text": "equal to amounts that are given or bequeathed for the purposes of amounts to\nTrust\nthe Trust Account and as provided in the Schedule. Account"
    },
    {
      "number": "43",
      "heading": "The purposes of the Trust Account are\u2014",
      "text": "Purposes of\nTrust\n(a) to provide assistance\u2014 Account\n(i)to the Departments of the Ministries responsible\nfor human and animal health that are engaged\nin health research;\n30 No. 2 of 2013] National Health Research\n(ii) to universities for the purpose of health research;\n(iii) to research institutions and health researchers\nengaged in health research; and\n(iv) for the training of persons in health research;\nand\n(b) provide for any other purpose that is prescribed for the\npurpose of this section.\n(2) Any assistance provided under subsection (1) shall be\nprovided in such cases and subject to such conditions as the Minister,\nacting on the advice of the Authority, shall determine.\n(3) Without limiting the generality of the conditions to which a\ngrant of assistance may be made under subparagraphs (i) (ii) or\n(iii) of paragraph (a) of subsection (1), such assistance shall be\nprovided if the recipient agrees to comply with the regulatory\nframework in force relating to the conduct of health research and\nsigns a research grant.\nAccounting 44. (1) Notwithstanding the other provisions of this Act, but\nfor gifts and\nsubject to subsection (2) and the Public Finance Act, 2004, any\nbequests\nAct No. 15 money that is\u2014\nof 2004\n(a) held by the Authority on trust for the purposes of the\nTrust Account; or\n(b) accepted by the Authority for the purposes of the Trust\nAccount which is subject to a condition;\nshall not be dealt with except in accordance with this Act, the\ncondition and the obligations of the trustees as set out in a Trust to\nbe established by the Minister for the purposes of this Act.\n(2) There shall be kept separate accounts of each sum of money\nstanding to the credit of the Trust Account that represents an amount\ngiven as a gift or bequest for specific health research.\nPART V\nHEALTH RESEARCH ON, OR EXPERIMENTATION WITH HUMAN\nPARTICIPANTS AND ANIMAL SUBJECTS\nHealth 45. (1) Health research or experiments on a human participant\nresearch on,\nshall be conducted\u2014\nor\nexperimentation\nwith, human (a) in the prescribed manner consistent with this Act;\nparticipants\nor animal (b) with the written consent of the person, after the person\nsubjects\nhas been informed of the objectives of the research or\nNational Health Research [ No. 2 of 2013 31\nexperimentation and any possible potential risks or\nbenefits on that person\u2019s health;\n(c) in the case of a deceased person, with written consent as\nprovided in the Human Tissue Act;\n(d) if it does not threaten national security;\n(e) if it does not violate social and cultural norms; and\n(f) in Zambia, with ethical approval by the Board or accredited\nhealth research ethics committee in accordance with\nthis Act. Cap. 306\n(2) Research involving human participants shall embrace all the\nfollowing basic pillars of health research ethics:\n(a) respect of persons (autonomy);\n(b) benefit to the research participants (beneficence); and\n(c) equal distribution of risks and benefits (justice).\n(3) The following elements shall be adhered to in conducting\nhealth research on human participants:\n(a) social or scientific value;\n(b) scientific validity;\n(c) fair selection of participants;\n(d) favourable risk benefit ratio;\n(e) informed consent;\n(f) respect of participants;\n(g) confidentiality;\n(h) protection of interests of stakeholders;\n(i) good clinical and laboratory practice; and\n(j) independent review.\n(4) Health research on a minor for therapeutic purposes shall be\nconducted\u2014\n(a) if it is in the best interest of the minor;\n(b) in such manner and on such conditions as may be prescribed\nin a regulatory framework;\n(c) with the consent of the parent or legal guardian of the\nminor; and\n(d) if the minor is capable of understanding the nature and\n32 No. 2 of 2013] National Health Research\nthe potential risks and benefits of the health research,\nwith the consent of the minor.\n(5) Health research on a minor for non therapeutic purposes\nshall be conducted \u2014\n(a) in such manner and on such conditions as may be\nprescribed;\n(b) with the consent of the Authority;\n(c) with the consent of the parent or legal guardian of the\nminor; and\n(d) if the minor is capable of understanding the nature and\npotential risks and benefits of the health research, the\nconsent of the minor.\n(6) The Authority shall not consent to a health research under\nparagraph (b) of subsection (5), in circumstances where\u2014\n(a) the objectives of the health research or experimentation\nmay also be achieved if it is conducted on an adult;\n(b) the health research or experimentation is not likely to\nsignificantly improve scientific understanding of the\nminor\u2019s condition, disease or disorder to such an extent\nthat shall result in significant benefit to the minor;\n(c) the reasons for the consent to the health research or\nexperimentation by the parent or guardian of the minor\nand, if applicable, the minor, are contrary to social norms\nand public policy;\n(d) the health research or experimentation poses a significant\nrisk to the health of the minor; or\n(e) there is s"
    },
    {
      "number": "48",
      "heading": "Notwithstanding any other law, biological material for health Purposes of",
      "text": "research shall only be collected for the purposes for which it is collection of\nbiological\nindicated in the research protocol. materials"
    },
    {
      "number": "49",
      "heading": "The Minister shall designate specific research Storage of",
      "text": "biological\ninstitutions and sites as bio-banks in accordance with section fifty-\nmaterials\none, and grant a licence, in the prescribed manner, to research\ninstitution, site or health establishment which are able to provide\nstorage services.\n(2) A bio-bank shall comply with the provisions of the\nEnvironmental Management Act, 2011, and the Health Professions Act No. 12\nAct, 2009. of 2011\nAct No. 24\n(3) A person, other than the holder of a licence granted in of 2009\naccordance with subsection (1), who keeps biological materials\ncommits an offence and is liable, upon conviction, to a fine not\nexceeding two million penalty units or to imprisonment for a term\nnot exceeding four years, or to both."
    },
    {
      "number": "50",
      "heading": "A person shall not export or import biological materials Exportation",
      "text": "without the prior written approval of the Authority as provided under and\nimportation\nsubsection (2).\nof biological\nmaterials\n(2) The Authority may, on the recommendation of the Board,\npermit the export or import of biological materials if all the prescribed\nelements of a material transfer agreement are met.\n(3) A person who contravenes this section commits an offence\nand is liable, upon conviction, to a fine not exceeding two million\npenalty units or to imprisonment for a period not exceeding four\nyears, or to both."
    },
    {
      "number": "51",
      "heading": "The Minister may, by notice in the Gazette, designate Designation",
      "text": "of\nany research institution, site or health establishment as a bio-bank.\ninstitution as\nbio-bank\n(2) A research institution, site or health establishment designated\nas a bio-bank under subsection (1), may\n(a) receive biological materials for storage purposes;\n(b) store biological material remnants for a period not\nexceeding ten years, unless the Authority approves a\nlonger period of time for special reasons; and\n(c) dispose of biological materials that are due for disposal\nfollowing prescribed bio-hazard waste guidelines.\n36 No. 2 of 2013] National Health Research\nSearches at 52. (1) An officer authorised under the Public Health Act,\nports of\nIonising Radiation Protection Act, 2005, and Immigration and\nentry, exit\nand sites Deportation Act, 2010, and any other relevant law enforcement\nCap. 295\nAct No. 16 officer may conduct a search, at any reasonable time, at any site,\nof 2005\nport of entry and port of exit.\nAct No. 18\nof 2010\n(2) Any biological material that is found to have been transferred\nwithout the necessary approvals and supporting documentation, as\nrequired under this Act, shall be confiscated and the person\ntransferring the biological material commits an offence and is liable\nto the general penalty.\nOwnership of 53. (1) The Minister shall, in consultation with the Authority,\nbiological prescribe and specify the requirements and contents of a material\nmaterials and\ntransfer agreement and shall provide for the terms and conditions\nmaterial\ntransfer regarding\u2014\nagreement\n(a) ownership of the material, including any of its derivatives\nand modifications; and\n(b) intellectual property rights, publication rights, the various\nuses of the material, including reproduction and\nreplication, confidentiality of information and transfer\nto third parties and liabilities.\nPART VII\nCLINICAL TRIALS\nClinical trials 54. (1) The Minister, in consultation with the Authority, shall\nmake regulations for the conduct of clinical trials in Zambia.\n(2) The Minister may constitute a special expert review panel\non matters of public interest, public policy or national security\nconcerning the conduct of clinical trials.\n(3) A medicine to be used in a clinical trial shall be approved by\nthe Zambia Medicines and Regulatory Authority as prescribed under\nAct No. of the Medicines and Allied Substances Act, 2013.\n2013\n(4) A clinical trial on human beings shall only be conducted\u2014\n(a) in the prescribed manner;\n(b) if the researcher is in possession of a letter of approval\nissued by the relevant research ethics committee;\nNational Health Research [ No. 2 of 2013 37\n(c) if the researcher has a clinical trial certificate issued by\nthe Zambia Medicines Regulatory Authority;\n(d) has ethical approval granted by the Board;\n(e) in accordance with Part V; and\n(f) with proven evidence of being in possession of a no fault\ninsurance for all research participants.\nPART VIII\nRESEARCH IN TRADITIONAL, COMPLEMENTARY AND ALTERNATIVE\nMEDICINE"
    },
    {
      "number": "55",
      "heading": "The Minister, in consultation with the Authority shall\u2014 Research in",
      "text": "traditional,\n(a) make regulations for facilitating health research in traditional, complementary\nand alternative\ncomplementary and alternative medicine in Zambia;\nmedicine\n(b) ensure wide dissemination of information on traditional,\ncomplementary and alternative medicine;\n(c) foster collaborative research between and among\ntraditional and conventional health researchers and\nresearch institutions; and\n(d) ensure that nothing in the execution of this Act prevents\ntraditional health practitioners from individually or\ncollectively protecting their intellectual property rights\nand indigenous knowledge relating to the processing of\ntheir medicinal preparations or final products.\nPART VIX\nINTELLECTUAL PROPERTY RIGHTS"
    },
    {
      "number": "56",
      "heading": "Any intellectual property rights arising from, or Intellectual",
      "text": "connected with, health research undertaken under this Act shall be property\nrights\nprotected under the relevant laws and a health researcher or\nresearch institutions shall be entitled to the full dissemination of\ninformation and benefits of the health research.\n(2) Notwithstanding subsection (1), a research institution or a\nhealth researcher shall patent and hold rights of all innovations and\ninventions that are products of dedicated and original scientific\nresearch under the relevant laws relating to registration of\nintellectual property rights.\n38 No. 2 of 2013] National Health Research\nPART X\nGENERAL PROVISIONS\nEntry by 57. (1) An inspector, agent of the Authority or any person\ninspectors or\nauthorised by the Authority for the purpose, may at any reasonable\nother\nauthorised time, enter on to any site and inspect the site, after giving reasonable\npersons\nnotice to a health researcher or person responsible for a research\ninstitution, for the purpose of ensuring compliance with this Act.\n(2) Notwithstanding subsection (1), an inspector may enter a\nsite or premises for purposes of this Act, with warrant, if the\ninspector has reasonable grounds to believe that a provision of this\nAct or of any other regulatory framework has been or is about to\nbe contravened or the site or premises are used or are being used\nfor the commission of an offence.\n(3) If so requested by a health researcher or person responsible\nfor a research institution, an inspector, agent of the Authority or a\nperson authorised by the Authority shall produce evidence of the\nauthorisation or permission, as the case may be, to enter on to the\nsite or premises.\n(4) A person exercising any power under this section shall do so\nwith reasonable care and in such a manner as to cause as little\ndamage as possible.\nDuty to 58. (1) A health researcher or research institution and any\nprovide\nemployee or agent of a health researcher or research institution\ninformation\nto inspector shall, on demand by an inspector\u2014\n(a) avail to the inspector such information as is within their\nknowledge in all matters relating to any inspection or\ninvestigation done under this Act; and\n(b) produce for inspection, any research protocol, licence,\nmaterial transfer agreement or other document or record,\nas the case may be, relating to the health research being\nundertaken on the site or any matter that is the cause\nfor the inspection or investigation.\n(2) A person who contravenes subsection (1) commits an offence\nand is liable, upon conviction, to the general penalty provided under\nthis Act.\nService of 59. (1) Any notice required to be served under this Act shall\nnotice\nbe served\u2014\n(a) by delivering it personally to the person required to be\nserved or, if the person is absent or cannot be found\nNational Health Research [ No. 2 of 2013 39\n(i)by leaving it at the person\u2019s usual or last known\nplace of abode in Zambia; or\n(ii) by registered post, addressed to the person\u2019s usual\nor last known address in Zambia; or\n(b) in the case of a notice required to be served on a company\nor other corporate body, by delivering it to its principal\nofficer, leaving it at the office with an employee or\nsending it through registered post."
    },
    {
      "number": "60",
      "heading": "Any direction, notice, consent, approval, permission, Authentication",
      "text": "demand, objection, application or other thing authorised or required of\nby this Act to be given, made or issued by, or to, the Minister, the documents\nAuthority, the Council, Board, Director or health research ethics\ncommittee shall be in writing.\n(2) A direction, notice, consent, approval, demand or other\ndocument which the Authority is authorised or required by or under\nthis Act to give, make or issue may be signed on behalf of the\nAuthority by\u2014\n(a) the Director or Secretary; or\n(b) an officer of the Authority authorised by the Director, in\nwriting, to sign documents of the particular kind or to\nsign the particular document."
    },
    {
      "number": "61",
      "heading": "A person who commits an offence under this Act shall, General",
      "text": "if no other penalty is specified or prescribed in respect of the penalties for\noffences\noffence, be liable, upon conviction, to a fine not exceeding three\nhundred thousand penalty units or to imprisonment for a term not\nexceeding three years, or to both.\n(2) In addition to the penalties, specified under subsection (1),\nany contravention of this Act or any regulations made under this\nAct shall be a ground for terminating a research protocol, licence\nor any permission or approval given under this Act.\n(3) Where a person is convicted of an offence under this Act\nany research material or substance relating to the research shall\nbe forfeited to the State."
    },
    {
      "number": "62",
      "heading": "Where an offence under this Act is committed by a body Offences by",
      "text": "body\ncorporate or an unincorporate body, every director or manager of\ncorporate or\nthe corporate or unincorporate body is liable, upon conviction, as an\nunincorporate\nif the director or manager had personally committed the offence, body\nunless the director or manager proves to the satisfaction of the\ncourt that the act constituting the offence was done without the\n40 No. 2 of 2013] National Health Research\nknowledge, consent or connivance of the director or manager or\nthat the director or manager took reasonable steps to prevent the\ncommission of the offence."
    },
    {
      "number": "63",
      "heading": "The Minister may, in consultation with the Authority, by",
      "text": "Regulations\nstatutory instrument, make regulations for the better carrying out\nof the provisions of this Act.\nTransitional 64. (1) The National Health Research Advisory Committee\nprovisions established by the Ministry responsible for health shall cease to\nexist three months after the constitution of the Authority.\n(2) Any health research related rights, liabilities, legal proceedings\nor obligations of the National Health Research Advisory Committee\nor any committee or research body established under the Ministry\nresponsible for health which are transferrable shall without further\nassurance be transferred to the Authority.\nNational Health Research [ No. 2 of 2013 41\nSCHEDULE\n(Sections 4 (2) and 42)\nTHE NATIONAL HEALTH RESEARCH AUTHORITY\nPART 1\nADMINISTRATION OF AUTHORITY"
    },
    {
      "number": "1",
      "heading": "The seal of the Authority shall be such device as may Seal of",
      "text": "be determined by the Authority and shall be kept by the Secretary. Authority\n(2) The affixing of the seal shall be authenticated by the\nChairperson or the Vice-Chairperson and the Secretary or any\nother person authorised in that behalf by a resolution of the Council.\n(3) Any contract or instrument which, if entered into or executed\nby a person not being a body corporate, would not be required to\nbe under seal, may be entered into or executed without seal on\nbehalf of the Authority by the Secretary or any other person generally\nor specifically authorised by the Council in that behalf.\n(4) Any document purporting to be a document under the seal of\nthe Authority or issued on behalf of the Authority shall be received\nin evidence and shall be deemed to be so executed or issued, as the\ncase may be, without further proof, unless the contrary is proved."
    },
    {
      "number": "2",
      "heading": "A member of the Council shall, subject to the other Tenure of",
      "text": "provisions of this Schedule, hold office for a term of three years office\nand vacancy\nand may be re-appointed for a further term of three years. of\nmember\n(2) Upon the expiration of the term for which a member is\nappointed, the member shall continue to hold office until another\nmember is appointed, but in no case shall any extension of the\nperiod exceed three months.\n(3) The office of a member becomes vacant\u2014\n(a) upon the member\u2019s death;\n(b) if the member is adjudged bankrupt;\n(c) if the member is absent, without reasonable excuse, from\nthree consecutive meetings of the Authority of which\nthe member had notice, without the prior approval of\nthe Authority;\n(d) upon the expiry of one month\u2019s notice of the member\u2019s\nintention to resign, given by the member, in writing, to\nthe Minister;\n42 No. 2 of 2013] National Health Research\n(e) if the member becomes mentally or physically incapable\nof performing duties as a member; or\n(f) if the member is convicted of an offence under this Act or\nany other law.\nFilling of 3. The Minister may, where the office of a member becomes\ncasual vacant before the expiry of the term of office, appoint another\nvacancy\nmember in place of the member who vacates office, but that member\nshall hold office only for the unexpired part of the term."
    },
    {
      "number": "4",
      "heading": "Subject to this Act, the Council may regulate its own",
      "text": "Proceedings\nof procedure.\nCouncil\n(2) The Council shall meet for the transaction of business at\nleast once in every three months at such places and times as the\nChairperson may determine.\n(3) The Chairperson may, upon giving notice of not less than\nfourteen days, call a meeting of the Council and shall call a special\nmeeting to be held within fourteen days of receipt of a written\nrequest to the Chairperson by at least five members of the Council.\n(4) If the urgency of any particular matter does not permit the\ngiving of such notice as is required under subparagraph (3), a special\nmeeting may be called by the Chairperson, upon giving a shorter\nnotice.\n(5) Seven members of the Council shall form a quorum at any\nmeeting of the Council.\n(6) There shall preside at any meeting of the Council\u2014\n(a) the Chairperson; and\n(b) in the absence of the Chairperson, the Vice Chairperson,\nand in the absence of the Chairperson and the Vice\nChairperson, such member as the members present may\nelect for the purpose of that meeting.\n(7) A decision of the Council on any question shall be by a majority\nof the members present and voting at the meeting and in the event\nof an equality of votes, the person presiding at the meeting shall\nhave a casting vote in addition to the deliberative vote.\n(8) The Council may invite any person, including any\nrepresentative of the Council or any health research ethics\ncommittee, whose presence is in its opinion desirable, to attend and\nto participate in the deliberations of the meeting of the Council but\nsuch person or representative shall not have any vote.\nNational Health Research [ No. 2 of 2013 43\n(9) The validity of any proceedings, act or decision of the Council\nshall not be affected by any vacancy in the membership of the\nCouncil or by any defect in the appointment of any member or by\nreason that any person not entitled to do so took part in the\nproceedings."
    },
    {
      "number": "5",
      "heading": "The members of the Council, the Board or any committee Allowances",
      "text": "shall be paid such allowances as the Council may, with the approval for\nmembers\nof the Minister, determine."
    },
    {
      "number": "6",
      "heading": "If a member or any person is present at a meeting of the Disclosure",
      "text": "Council or any committee of the Council at which any matter is the of\ninterest\nsubject of consideration and in which matter the member or that\nperson or the member\u2019s or that person\u2019s relative is directly or\nindirectly interested, in a private capacity, is the subject of\nconsideration, the member or person shall, as soon as is practicable,\nafter the commencement of the meeting, declare such interest and\nshall not, unless the Council or the committee otherwise directs,\ntake part in any consideration or discussion of, or vote on, any\nquestion touching that matter.\n(2) A declaration of interest made under this paragraph shall be\nrecorded in the minutes of the meeting at which it is made.\n(3) In this paragraph, \u201c relative \u201d in relation to a person means\u2014\n(a) a parent, son, daughter, brother, sister, niece, uncle, aunt,\ngrandparent or cousin of that person or that person\u2019s\nspouse; and\n(b) a spouse of that person."
    },
    {
      "number": "7",
      "heading": "A person shall not, without the consent, in writing, given Prohibition",
      "text": "by, or on behalf of, the Authority, publish or disclose to any of\npublication\nunauthorised person, otherwise than in the course of duties of that\nor disclosure\nperson, the contents of any document, communication or information\nof\nwhatsoever, which relates to or which has come to the knowledge information\nof that person in the course of that person\u2019s duties under this Act. to\nunauthorised\n(2) A person who contravenes subparagraph (1) commits an\npersons\noffence and is liable, upon conviction, to a fine not exceeding three\nhundred thousand penalty units or to imprisonment for a period not\nexceeding two years, or to both.\n(3) A person who, having any information which to the knowledge\nof that person has been published or disclosed in contravention of\nsubparagraph (1), unlawfully publishes or communicates the\ninformation to any other person, commits an offence and is liable,\n44 No. 2 of 2013] National Health Research\nupon conviction, to a fine not exceeding three hundred thousand\npenalty units or to imprisonment for a period not exceeding two\nyears, or to both."
    },
    {
      "number": "8",
      "heading": "An action or other proceeding shall not lie or be instituted",
      "text": "Immunity\nagainst a member of the Council, the Board or a committee of the\nBoard for, or in respect of, any act or thing done or omitted to be\ndone in good faith in the exercise or performance of, or purported\nexercise or performance of, any of the powers, functions or duties\nconferred under this Act.\nPART II\nFINANCIAL PROVISIONS\nFunds of 9. (1) The funds of the Authority shall consist of such moneys\nAuthority as may\u2014\n(a) be appropriated to the Authority by Parliament for the\npurposes of the Authority;\n(b) be paid to the Authority by way of fees, charges, grants\nor donations;and\n(c) otherwise vest in or accrue to the Authority.\n(2) The Authority may\u2014\n(a) accept moneys by way of grants, gifts, bequests or\ndonations from any source in Zambia and subject to the\nprior approval of the Minister, in writing, from any source\noutside Zambia;\n(b) subject to the approval of the Minister, raise by way of\nloans or otherwise, such moneys as it may require for\nthe discharge of its functions; and\n(c) in accordance with the regulations made under this Act,\ncharge fees for services provided by the Authority.\n(3) There shall be paid from the funds of the Authority\u2014\n(a) salaries, allowances, loans, gratuities and pensions of staff\nof the Authority, and other payments for the recruitment\nand retention of staff;\n(b) such reasonable travelling and subsistence allowances\nfor members, members of the Board or any committee\nof the Council, when engaged on the business of the\nAuthority at such rates as the Minister may determine;\nand\nNational Health Research [ No. 2 of 2013 45\n(c) any other expenses incurred by the Authority in the\nperformance of its functions.\n(4) Notwithstanding subsections (1), (2) and (3) any moneys\npaid to the Authority as bequests and donations or grants for health\nresearch shall be paid into the Trust Account.\n(5) The Authority may, after the approval of the Minister, invest\nin such manner as it thinks fit such of its funds as it does not\nimmediately require for the discharge of its functions."
    },
    {
      "number": "10",
      "heading": "The financial year of the Authority shall be the period of Accounts",
      "text": "twelve months ending on 31st December of each year. and audit"
    },
    {
      "number": "11",
      "heading": "The Authority shall cause to be kept proper books of Financial",
      "text": "accounts and other records relating to its accounts. years\n(2) The Authority shall, within ninety days of the expiry of the\nfinancial year, submit to the Minister a report concerning its activities\nduring the financial year.\n(3) The report referred to in subparagraph (2) shall include\nstatements of income and expenditure and a statement of affairs\nor balance sheet.\n(4) The accounts of the Authority shall be audited annually or\nwhenever necessary by the Auditor General."
    },
    {
      "number": "12",
      "heading": "As soon as practicable, but not later than ninety days Annual",
      "text": "after the end of the financial year, the Authority shall submit to the report\nMinister a report concerning its activities and the activities of the\nBoard during the financial year.\n(2) The report referred to in subparagraph (1) shall include\ninformation on the financial affairs of the Authority and there shall\nbe appended to the report\u2014\n(a) an audited balance sheet;\n(b) an audited statement of income and expenditure; and\n(c) such other information as the Minister may require.\n(3) The Minister shall not later than seven days after the first\nsitting of the National Assembly next after receipt of the report\nreferred to in subparagraph (1), lay the report before the National\nAssembly."
    }
  ],
  "source_url": "https://www.parliament.gov.zm/sites/default/files/documents/acts/Health%20%20Research%20%20Act%202013.pdf",
  "source_hash": "sha256:33c48cfb303e948069ba56b59f61877baca1269e2eb9f593d6357e298da08683",
  "fetched_at": "2026-04-11T14:57:15Z",
  "parser_version": "0.1.0"
}