{
  "id": "act-zm-2024-026-revenue-authority-2024",
  "type": "act",
  "jurisdiction": "ZM",
  "title": "Zambia Revenue Authority (Amendment) Act, 2024",
  "citation": "Act No. 26 of 2024",
  "version_type": "as_enacted",
  "in_force": null,
  "amended_by": [],
  "sections": [
    {
      "number": "2",
      "title": "The principal Act is amended by the repeal of section 18 Repeal and",
      "body": "replacement\nand the substitution therefor of the following:\nof section 18",
      "page_start": 1
    },
    {
      "number": "18",
      "title": "An action or other proceedings shall not lie or Immunity of",
      "body": "be instituted against a member, a member of a committee members and\nstaff\nor a member of staff of the Authority for, or in respect of,\nan act or thing done or omitted to be done in good faith in\nthe exercise or performance of any of the powers,\nfunctions or duties conferred under this Act.\nSingle copies of this Act may be obtained from the Government Printer,\nP.O. Box 30136, 10101 Lusaka, Price K 4.00 each.\n400",
      "page_start": 1
    }
  ],
  "source_url": "https://www.parliament.gov.zm/sites/default/files/documents/acts/Act%20No.%2026%20of%202024%20Zambia%20Revenue%20Authority%20Act.pdf",
  "source_hash": "sha256:f381a4a0d8560d1820eaf7426350e1f6d62327f294b5771519a39b72aeabd959",
  "fetched_at": "2026-04-10T09:43:50Z",
  "parser_version": "0.3.0",
  "notes": "Phase 4 Batch 001. Node URL: https://www.parliament.gov.zm/node/12081. PDF size: 282729 bytes. Parse notes: WARN: only 2 section headings found — parse may be incomplete"
}