{
  "id": "si-zm-2017-077-national-markets-and-bus-stations-development-fund-regulations-2017",
  "type": "statutory_instrument",
  "jurisdiction": "ZM",
  "year": 2017,
  "number": 77,
  "title": "National Markets and Bus Stations Development Fund Regulations, 2017",
  "parent_act": "Markets and Bus Stations Act",
  "sub_phase": "sis_local_government",
  "effective_date": "2017-12-15",
  "source_url": "https://zambialii.org/akn/zm/act/si/2017/77",
  "source_pdf_url": "https://zambialii.org/akn/zm/act/si/2017/77/eng@2017-12-15/source.pdf",
  "source_hash": "2b2196bea4984851c471b5919761d08251e31b465f70a7ea553a02913f856337",
  "html_hash": "c88877af552a66ccb3599da4858b4d2b87b2144b195bef4b04b38b3d585e958f",
  "fetched_at": "2026-04-25T12:36:38Z",
  "parser_version": "0.5.0",
  "pdf_pages": 18,
  "pdf_text_chars": 24051,
  "amended_by": [],
  "repealed_by": [],
  "cited_authorities": []
}