{
  "id": "judgment-zm-2025-zmsc-19-roanbeat-v-mtn",
  "type": "judgment",
  "jurisdiction": "ZM",
  "title": "Roanbeat Investment Limited v MTN (Zambia) Limited and Anor (SCZ/7/22/2024) [2025] ZMSC 19 (13 August 2025)",
  "citation": "[2025] ZMSC 19",
  "case_number": "SCZ/7/22/2024",
  "court": "Supreme Court of Zambia",
  "delivery_date": "2025-08-13",
  "parties": {
    "appellant": [
      "Roanbeat Investment Limited"
    ],
    "respondent": [
      "MTN Limited and Anor"
    ]
  },
  "judges": [],
  "cited_authorities": [],
  "paragraphs": [
    {
      "number": "1",
      "text": "D. E. Nkhuwa v. Lusaka Tyre Services Limited (1977) ZR 43"
    },
    {
      "number": "2",
      "text": "Investrust Bank Plc v. Buildit Hardware Ltd (SCZ/ Appeal No.\n003/2013)"
    },
    {
      "number": "3",
      "text": "Twampane Mining Corporation Limited and E & M Storti Mining\n(2011) ZR 67"
    },
    {
      "number": "4",
      "text": "Palata Investments Ltd and Others v. Burt & Sin.field Ltd and Others\n(1985)ALLE.R. 517\nR2\nLegislation referred to:"
    },
    {
      "number": "1",
      "text": "Court ofA ppeal Act"
    },
    {
      "number": "2",
      "text": "Supreme Court Act\n1.0. INTRODUCTION\n1.1. On 4th April 2025, Kabuka JS sitting as a single judge of this\ncourt delivered a ruling in which she declined the applicant's\napplication for extension of time within which to file an\napplication for leave to appeal a Court of Appeal judgment.\n1.2. The application before Kabuka JS, was made against some\nrather unusual circumstances. It came after the Court of\nAppeal on 29th August 2023 delivered a judgment against the\nrespondents in favour of the applicant to this motion.\n1.3. The applicant was the successful party in the action in the High\nCourt. The judgment of the High Court was upheld by the Court\nof Appeal. It is not often that a party who prevails in court\nproceedings contemplates an appeal against the verdict, as did\nthe applicant in this case.\n1.4. It would appear that the applicant's dissatisfaction arose\nprincipally from the holdings that the party primarily liable to\nR3\npay damages to the applicant was the second respondent who\nhad previously undertaken to indemnify the first respondent.\n1.5. Leave to appeal to this court was declined by the Court of Appeal\nin a ruling given on 12th July 2024. The court held that the\nproposed grounds of appeal as formulated neither raised any\npoint of law of public importance nor did they have any prospect\nof success.\n1.6. Still desirous of prosecuting the appeal, the applicant then\nconsidered filing a renewed application before a single judge of\nthis court for leave to appeal. This was, however, conceived way\nbeyond the time prescribed for making such applications.\nAccordingly, the applicant sought an order for extension of time\nwithin which to file the application for leave to appeal.\n2.0. APPLICATION FOR EXTENSION OF TIME BEFORE A SINGLE JUDGE\n2.1. The application was made ex-parte to a single judge of this\ncourt. It was filed on 17th September 2024. The single judge\npreferred that the application was heard inter-partes, and so it\nwas on 10th October 2024.\nR4\n2.2. The affidavit in support of the application for extension of time\nwas sworn by Ronald Bwale Nsokoshi, a director in the\napplicant company. He averred that he was in South Africa at\nthe time the ruling by the Court of Appeal refusing to grant\npermission to appeal was made. He further states that the\napplicant's Advocates on record were unable to contact him and\ncommunicate the decision of the Court of Appeal, and to obtain\nfurther instructions.\n2.3. The deponent swore that he only came to know the outcome of\nthe applicant's application for permission to appeal upon his\nreturn on 15th August 2024. He produced stamped copies of\nhis passport to confirm that he was out of the country when the\nruling was delivered.\n2.4. The applicant then changed lawyers from Makebi Zulu and Co.,\nto Zamb we and Partners. The latter only received the case\nrecords from the farmer on 19th August 2024.\n2.5. In his affidavit the deponent reiterated his belief that the\nproposed appeal raises an important and novel question of law\nof public importance which this court ought to determine.\nRS\n3.0. APPLICATION OPPOSED\n3.1. The application was opposed. On behalf of the first respondent,\nthe opposing affidavit was sworn by Wana Mukuma, its Legal\nAssistant.\n3.2. The basis for the opposition was principally that Ronald Bwale\nNsokoshi is not the only Director in the applicant company as\nthe exhibited PACRA records show; that the applicant was made\naware of the ruling of the Court of Appeal declining permission\nto appeal on 22 nd July 2024. A letter from Zambwe and\nPartners, lawyers for the applicant and dated 16th August 2024,\naddressed to Makebi Zulu & Co., former lawyers of the\napplicant, was exhibited. It confirms that the ruling was\nnd\nreceived by the applicant on 22 July 2024.\n3.3. Wana Mutale further deposed that despite knowing of the ruling\non 22nd July 2024 the applicant waited until 11th September\n2024 to file the application. In any case, he averred, there are\nmultiple forms of communication which could have been used\nto inform the one director of the applicant who was out of the\ncountry.\nR6\n4.0. DECISION OF THE SINGLE JUDGE\n4.1. Upon hearing the parties and appraising the affidavits and the\narguments submitted, the single judge reviewed various\nauthorities and in her ruling of 4th April 2025 held that the delay\nby the applicant in lodging a renewed application for leave to\nappeal was inordinate. The reason given for the delay was not\nsatisfactory. She thus declined to grant the application for\nextension of time.\n4.2. The applicant then, by motion to the full court, renewed the\napplication for extension of time to file the renewed application\nfor leave to appeal.\n5.0. CONSIDERATION OF THE RENEWED APPLICATION\n5.1. The factual premises for the current application 1s straight\nforward. The applicant had applied for leave to appeal the\ndecision of the Court of Appeal in obedience to section 13(3) of\nthe Court of Appeal Act. That application was rejected by the\nCourt of Appeal.\nR7\n5.2. The applicant then sought to renew the application by moving\na single judge of this court in accordance with section 24(b) of\nthe Supreme Court Act.\n5.3. Section 17(1) of the Supreme Court Act provides that:\n... a person who intends to appeal against a judgment of the\nCourt of Appeal shall do so within 14 days of obtaining leave\nfrom the Court of Appeal in the manner and form prescribed by\nthe rules of the Court of Appeal.\n5.4. In the present case leave by the Court of Appeal was declined.\nThe applicant thus sought to renew the application for leave\nbefore a single judge of this court. Such application, like that\nenvisaged in section 17 of the Supreme Court Act as quoted\nabove, is time bound.\n5.5. In terms of Rule 48(1) as amended, an application to a single\njudge shall be by motion or summons within fourteen days of\nthe decision complained of. In this case, this translates to\nfourteen days after the 12th July 2024.\n5.6. This court, however, has the power to grant extension of time\nwithin wh"
    },
    {
      "number": "5",
      "text": "7. In considering whether to grant the extension sought, the court\nwill review the reason given for the delay, the length of the delay,\nthe prejudice to the other party and, in some cases, the merits\nof the application or the objective the order sought is intended\nto achieve.\n5.8. In D. E. Nkhuwa v. Lusaka Tyre Services Limitedl11, we stated in\nrelation to an application for leave to appeal that:\nThe granting of an extension of time within which to appeal is\nentirely in the discretion of the court, but such discretion will\nnot be exercised without good cause.\n5.9. Elsewhere in that judgement we observed more generally, that:\nWhere the court has discretion to enlarge time for a procedural\nstep, it will not exercise that discretion in favour of the\napplicant unless there is some material on which the discretion\ncan be exercised. ..\nThe rules prescribing times within which steps must be taken\nmust be adhered to strictly and practitioners who ignore them\ndo so at their own peril.\nR9\n5.10. In Investrust Bank Plc v. Buildit Hardware Ltdl21 we pertinently\nobserved that the power vested in this court by virtue of Rule\n12 of the Supreme Court Rules is not unfettered; it is to be\nexercised only where it can be shown that there was sufficient\nreason to exercise the discretion to extend time.\n5.11. In the present case the applicant has stated that its director was\nout of jurisdiction and was thus unaware of the ruling of the\nCourt of Appeal declining leave. In this day and age, technology\nhas so advanced that only the willful can remain\nincommunicado, regardless of where they happen to be.\n5.12. Besides, the applicant is a limited liability company which is\ndomiciled in this Republic of Zambia. It does not fly to\nJohannesburg if one of its directors does. It is a going concern\nand it remained so at all material times.\n5.13. Evidence has been provided through the Affidavit in Opposition\nthat the lawyers for the applicant confirmed that the ruling was\nreceived by the applicant on 22nd July 2024.\nRIO\n5.14. There is further evidence confirming that another director was\navailable, even assuming that the applicant company had no\nmanagement. We find the reasons given for failure to file the\napplication within the prescribed period, incredible.\n5.15. As observed by the single judge some fifty odd days elapsed from\nthe time the applicant should have filed its application. In\nTwampane Mining Corporation Limited and E & M Storti Miningl3l we\nconsidered the length of the delay in making an application and\nconcluded that thirty-nine days was to long a delay. In Palata\nInvestments Ltd and Others v. Burt & Sinfield Ltd and Othersl4l on\nthe other hand, a delay of three days was considered to be short.\n5.16. In Investrust v. Buildit Hardware12l the application was filed fifty\ndays after the judgment. We considered the delay as inordinate.\nLikewise, in this case, we hold that a delay of fifty days is\ninordinate.\n5.17. The upshot is that we find the reasons given for the delay not to\nbe sufficient or good enough to enable us exercise our discretion\nin favour of the applicant. We also consider the period of fifty\nRll\ndays delay to be inordinate. We find it unnecessary to comment\non the prospect of the intended appeal.\n5.18. For the foregoing reasons, we uphold the decision of the single\njudge and dismiss this motion with costs to be truced in default\nof agreement.\n~::=-----\nCHIEF JUSTICE\n····················~ ······\nF. M. Chisanga\nSUPREME COURT JUDGE"
    }
  ],
  "source_url": "https://zambialii.org/akn/zm/judgment/zmsc/2025/19/eng@2025-08-13/source.pdf",
  "source_hash": "sha256:721ef79ff8b36f1a02860bf4183bc06275fce7f3f713c274e798286d70361581",
  "fetched_at": "2026-04-24T16:35:29Z",
  "parser_version": "0.5.0",
  "alternate_sources": [
    {
      "source_url": "https://zambialii.org/akn/zm/judgment/zmsc/2025/19/eng@2025-08-13",
      "source_hash": "sha256:a9f1752466305a31f66f0be12dee7f5e9ddfc268a315f5afb152d71fdb6c3c94",
      "fetched_at": "2026-04-24T16:35:25Z",
      "role": "discovery_and_title"
    }
  ],
  "rights_notice": "Publisher: ZambiaLII (African Legal Information Institute). Reproduction and retention by Kate Weston Legal Practitioners is under the fair-dealing exceptions of the Copyright and Performance Rights Act, Cap. 406 of the Laws of Zambia, for legal research and professional commentary. Judgments of the Supreme Court of Zambia are public acts of the state and are cited for their legal authority only.",
  "sensitive_data_categories": [
    "none"
  ]
}