{
  "id": "act-zm-1960-005-preservation-of-public-security-act-1960",
  "type": "act",
  "jurisdiction": "ZM",
  "title": "Preservation of Public Security Act, 1960",
  "citation": "Act No. 5 of 1960",
  "enacted_date": "1960-01-01",
  "commencement_date": null,
  "in_force": true,
  "amended_by": [],
  "repealed_by": null,
  "sections": [
    {
      "number": "",
      "heading": "",
      "text": "This Act may be cited as the Preservation of Public Security Act."
    },
    {
      "number": "",
      "heading": "",
      "text": "In this Act, the expression \"public security\" includes the securing of the safety of persons and property, the maintenance of supplies and services essential to the life of the community, the prevention and suppression of violence, intimidation, disorder and crime, the prevention and suppression of mutiny, rebellion and concerted defiance of, and disobedience to, the law and lawful authority, and the maintenance of the administration of justice.[As amended by G.N. No. 229 of 1964 and S.I. No. 85 of 1964]"
    },
    {
      "number": "(1)",
      "heading": "",
      "text": "(1)The provisions of this section shall have effect during any period when a declaration made under the Constitution has effect.\nThe provisions of this section shall have effect during any period when a declaration made under the Constitution has effect.\n(2)The President may, for the preservation of public security, by regulation\u2014(a)make provision for the prohibition of the publication and dissemination of matter prejudicial to public security, and, to the extent necessary for that purpose, for the regulation and control of the production, publishing, sale, supply, distribution and possession of publications;(b)make provision for the prohibition, restriction and control of assemblies;(c)make provision for the prohibition, restriction and control of residence, movement and transport of persons, the possession, acquisition, use and transport of movable property, and the entry to, egress from, occupation and use of immovable property;(d)make provision for the regulation, control and maintenance of supplies and services; or(e)make provision for, and authorise the doing of, such other things as appear to him to be strictly required by the exigencies of the situation in Zambia.\nThe President may, for the preservation of public security, by regulation\u2014\n(a)make provision for the prohibition of the publication and dissemination of matter prejudicial to public security, and, to the extent necessary for that purpose, for the regulation and control of the production, publishing, sale, supply, distribution and possession of publications;\nmake provision for the prohibition of the publication and dissemination of matter prejudicial to public security, and, to the extent necessary for that purpose, for the regulation and control of the production, publishing, sale, supply, distribution and possession of publications;\n(b)make provision for the prohibition, restriction and control of assemblies;\nmake provision for the prohibition, restriction and control of assemblies;\n(c)make provision for the prohibition, restriction and control of residence, movement and transport of persons, the possession, acquisition, use and transport of movable property, and the entry to, egress from, occupation and use of immovable property;\nmake provision for the prohibition, restriction and control of residence, movement and transport of persons, the possession, acquisition, use and transport of movable property, and the entry to, egress from, occupation and use of immovable property;\n(d)make provision for the regulation, control and maintenance of supplies and services; or\nmake provision for the regulation, control and maintenance of supplies and services; or\n(e)make provision for, and authorise the doing of, such other things as appear to him to be strictly required by the exigencies of the situation in Zambia.\nmake provision for, and authorise the doing of, such other things as appear to him to be strictly required by the exigencies of the situation in Zambia.\n(3)If the President is satisfied that the situation in Zambia is so grave that it is necessary so to do, he may, by statutory instrument, make regulations to provide for\u2014(a)the detention of persons;(b)requiring persons to do work and render services.[Cap. 1][As amended by S.I. No. 85 of 1964]\nIf the President is satisfied that the situation in Zambia is so grave that it is necessary so to do, he may, by statutory instrument, make regulations to provide for\u2014\n(a)the detention of persons;\nthe detention of persons;\n(b)requiring persons to do work and render services.\nrequiring persons to do work and render services."
    },
    {
      "number": "(a)",
      "heading": "",
      "text": "Regulations made under section three may\u2014\n(a)make provision for the payment of compensation and remuneration to persons affected by the regulations;\nmake provision for the payment of compensation and remuneration to persons affected by the regulations;\n(b)make provision for the apprehension and trial of persons offending against the regulations and for such penalties as the President may think fit for offenders thereunder;\nmake provision for the apprehension and trial of persons offending against the regulations and for such penalties as the President may think fit for offenders thereunder;\n(c)make provision for suspending the operation of any written law other than the Constitution;[Cap. 1]\nmake provision for suspending the operation of any written law other than the Constitution;[Cap. 1]\n(d)make provision for empowering such authorities and persons as may be specified in the regulations to make orders and rules for any of the purposes for which such regulations may be made;\nmake provision for empowering such authorities and persons as may be specified in the regulations to make orders and rules for any of the purposes for which such regulations may be made;\n(e)make provision for the delegation and transfer of powers and duties conferred and imposed by or under the regulations; and\nmake provision for the delegation and transfer of powers and duties conferred and imposed by or under the regulations; and\n(f)contain such other incidental and supplementary provisions as appear to the President to be necessary or desirable for the purposes of such regulations:\ncontain such other incidental and supplementary provisions as appear to the President to be necessary or desirable for the purposes of such regulations:"
    },
    {
      "number": "(1)",
      "heading": "",
      "text": "(1)Any regulations made under this Act may be made to apply to Zambia or to any part thereof, and to any person or class of persons or to the public generally.\nAny regulations made under this Act may be made to apply to Zambia or to any part thereof, and to any person or class of persons or to the public generally.\n(2)Subject to the provisions of section twenty-two of the Interpretation and General Provisions Act, any regulation made under this Act, and any order or rule made under any such regulation, shall have effect notwithstanding anything inconsistent therewith contained in any written law other than the Constitution and to the extent of any such inconsistency any such law as aforesaid shall have no effect so long as such regulation, order or rule shall remain in force.[Cap. 2; Cap. 1]\nSubject to the provisions of section twenty-two of the Interpretation and General Provisions Act, any regulation made under this Act, and any order or rule made under any such regulation, shall have effect notwithstanding anything inconsistent therewith contained in any written law other than the Constitution and to the extent of any such inconsistency any such law as aforesaid shall have no effect so long as such regulation, order or rule shall remain in force.[Cap. 2; Cap. 1]\n(3)Where any regulation made under this Act or any order or rule made under any regulation made under paragraph (d) of section four has not been laid before the National Assembly on a sitting day within three months of the date of making thereof, such regulation, order or rule shall, on the expiration of the said period of three months, cease to have effect, but without prejudice to the validity of anything previously done thereunder or to the making of any new regulation, order or rule.[As amended by G.N. No. 229 of 1964 and S.I. No. 85 of 1964]\nWhere any regulation made under this Act or any order or rule made under any regulation made under paragraph (d) of section four has not been laid before the National Assembly on a sitting day within three months of the date of making thereof, such regulation, order or rule shall, on the expiration of the said period of three months, cease to have effect, but without prejudice to the validity of anything previously done thereunder or to the making of any new regulation, order or rule.[As amended by G.N. No. 229 of 1964 and S.I. No. 85 of 1964]"
    },
    {
      "number": "",
      "heading": "",
      "text": "Every document purporting to be an order, licence, permit, certificate, direction, authority, or other document made, granted or issued by the Governor of Northern Rhodesia prior to the 24th October, 1964, or thereafter by the President, or any other authority or person in pursuance of this Act or any regulation made under this Act or any order or rule made under any such regulation, and purporting to be signed by or on behalf of the Governor of Northern Rhodesia prior to the 24th October, 1964, or thereafter by the President, or such other authority or person, shall be received in evidence, and shall, until the contrary is proved, be deemed to have been made, granted or issued by the Governor of Northern Rhodesia prior to the 24th October, 1964, or thereafter by the President, or that authority or person.[As amended by S.I. No. 85 of 1964]"
    }
  ],
  "source_url": "https://zambialii.org/akn/zm/act/1960/5/eng@1996-12-31",
  "source_hash": "sha256:8b94176066c38bac97eb42b9ccf802fd697ac4d813a755dcd19e5d5a1b3e16c0",
  "fetched_at": "2026-04-15T17:38:34Z",
  "parser_version": "0.5.0",
  "consolidated_as_of": "1996-12-31"
}